README.md
setup.py
Quart_Discord.egg-info/PKG-INFO
Quart_Discord.egg-info/SOURCES.txt
Quart_Discord.egg-info/dependency_links.txt
Quart_Discord.egg-info/not-zip-safe
Quart_Discord.egg-info/requires.txt
Quart_Discord.egg-info/top_level.txt
quart_discord/__init__.py
quart_discord/_http.py
quart_discord/client.py
quart_discord/configs.py
quart_discord/exceptions.py
quart_discord/utils.py
quart_discord/models/__init__.py
quart_discord/models/base.py
quart_discord/models/connections.py
quart_discord/models/guild.py
quart_discord/models/integration.py
quart_discord/models/user.py
tests/__init__.py
tests/test_app.py