Metadata-Version: 1.1
Name: Quart-Discord
Version: 2.0.0
Summary: Discord OAuth2 extension for Quart.
Home-page: https://github.com/jnawk/Quart-Discord
Author: Philip Dowie
Author-email: philip@jnawk.nz
License: MIT
Platform: any
Classifier: Environment :: Web Environment
Classifier: Intended Audience :: Developers
Classifier: License :: OSI Approved :: MIT License
Classifier: Operating System :: OS Independent
Classifier: Programming Language :: Python
Classifier: Topic :: Internet :: WWW/HTTP :: Dynamic Content
Classifier: Topic :: Software Development :: Libraries :: Python Modules
